retrywrap/__init__.py
retrywrap/decorator.py
retrywrap-0.1.0.dist-info/licenses/LICENSE
retrywrap-0.1.0.dist-info/METADATA
retrywrap-0.1.0.dist-info/WHEEL
retrywrap-0.1.0.dist-info/top_level.txt
retrywrap-0.1.0.dist-info/RECORD
